deinterlacing/__init__.py
deinterlacing/alignment.py
deinterlacing/offsets.py
deinterlacing/parameters.py
deinterlacing/processing.py
deinterlacing/tools.py
deinterlacing-1.0.5.dist-info/licenses/LICENSE
deinterlacing-1.0.5.dist-info/METADATA
deinterlacing-1.0.5.dist-info/WHEEL
deinterlacing-1.0.5.dist-info/top_level.txt
deinterlacing-1.0.5.dist-info/RECORD
