Metadata-Version: 2.4
Name: deinterlacing
Version: 1.0.5
Summary: A python library for deinterlacing images collected using resonant-scanning microscopes.
Author: Darik A. O'Neil
Maintainer: Darik A. O'Neil
License-Expression: MIT
Project-URL: documentation, https://github.com/darikoneil/resonant_deinterlacing
Project-URL: repository, https://github.com/darikoneil/resonant_deinterlacing
Keywords: deinterlacing,resonant,microscopy,image-processing,neuroscience,two-photon,imaging,optics,multiphoton,scanning,calcium imaging,voltage imaging
Classifier: Programming Language :: Python
Requires-Python: <=4.0,>=3.10
License-File: LICENSE
Requires-Dist: boltons
Requires-Dist: numpy>=2.0.0
Requires-Dist: pydantic>=2.11
Requires-Dist: scipy>=1.15.2
Requires-Dist: tqdm
Provides-Extra: test
Requires-Dist: importlib-metadata; extra == "test"
Requires-Dist: pytest; extra == "test"
Requires-Dist: pytest-sugar; extra == "test"
Requires-Dist: pytest-clarity; extra == "test"
Requires-Dist: toml; extra == "test"
Requires-Dist: tomli-w; extra == "test"
Provides-Extra: lint
Requires-Dist: flake8; extra == "lint"
Requires-Dist: flake8-annotations-complexity; extra == "lint"
Requires-Dist: flake8-class-attributes-order; extra == "lint"
Requires-Dist: flake8-dunder-all; extra == "lint"
Requires-Dist: flake8-html; extra == "lint"
Requires-Dist: ruff; extra == "lint"
Provides-Extra: cov
Requires-Dist: coverage[toml]; extra == "cov"
Requires-Dist: coveralls; extra == "cov"
Requires-Dist: toml; extra == "cov"
Requires-Dist: tomli-w; extra == "cov"
Provides-Extra: docs
Requires-Dist: sphinx; extra == "docs"
Requires-Dist: sphinx-autodoc-typehints; extra == "docs"
Requires-Dist: autodoc_pydantic; extra == "docs"
Requires-Dist: sphinx-rtd-theme; extra == "docs"
Provides-Extra: dev
Requires-Dist: deinterlacing[test]; extra == "dev"
Requires-Dist: deinterlacing[lint]; extra == "dev"
Requires-Dist: deinterlacing[cov]; extra == "dev"
Requires-Dist: deinterlacing[docs]; extra == "dev"
Dynamic: license-file
